odoo8_addon_l10n_it_ateco-8.0.1.0.1-nspkg.pth
odoo_addons/l10n_it_ateco/README.rst
odoo_addons/l10n_it_ateco/__init__.py
odoo_addons/l10n_it_ateco/__openerp__.py
odoo_addons/l10n_it_ateco/data/ateco_data.xml
odoo_addons/l10n_it_ateco/i18n/es.po
odoo_addons/l10n_it_ateco/i18n/it.po
odoo_addons/l10n_it_ateco/i18n/l10n_it_ateco.pot
odoo_addons/l10n_it_ateco/i18n/sl.po
odoo_addons/l10n_it_ateco/model/__init__.py
odoo_addons/l10n_it_ateco/model/ateco.py
odoo_addons/l10n_it_ateco/model/partner.py
odoo_addons/l10n_it_ateco/security/ir.model.access.csv
odoo_addons/l10n_it_ateco/static/description/icon.png
odoo_addons/l10n_it_ateco/view/ateco_view.xml
odoo_addons/l10n_it_ateco/view/partner_view.xml
odoo8_addon_l10n_it_ateco-8.0.1.0.1.dist-info/METADATA
odoo8_addon_l10n_it_ateco-8.0.1.0.1.dist-info/WHEEL
odoo8_addon_l10n_it_ateco-8.0.1.0.1.dist-info/namespace_packages.txt
odoo8_addon_l10n_it_ateco-8.0.1.0.1.dist-info/top_level.txt
odoo8_addon_l10n_it_ateco-8.0.1.0.1.dist-info/RECORD
